django_hide/__init__.py
django_hide/apps.py
django_hide/middleware.py
django_hide/templatetags/__init__.py
django_hide/templatetags/django_hide.py
django_hide-0.0.4.1.dist-info/LICENSE
django_hide-0.0.4.1.dist-info/METADATA
django_hide-0.0.4.1.dist-info/WHEEL
django_hide-0.0.4.1.dist-info/top_level.txt
django_hide-0.0.4.1.dist-info/RECORD
