Metadata-Version: 2.1
Name: django-hide
Version: 0.0.4.1
Summary: A Django package to obscure Django applications from detection tools like Wappalyzer by encrypting the CSRF token.
Home-page: https://github.com/metemaddar/django_hide
Author: Mohammad Etemaddar
Author-email: mohammad.etemaddar@gmail.com
Project-URL: Documentation, https://github.com/metemaddar/django_hide/blob/main/README.md
Project-URL: Source, https://github.com/metemaddar/django_hide
Project-URL: Tracker, https://github.com/metemaddar/django_hide/issues
Keywords: django security wappalyzer hide csrf
Classifier: Development Status :: 4 - Beta
Classifier: Framework :: Django
Classifier: Intended Audience :: Developers
Classifier: License :: OSI Approved :: MIT License
Classifier: Programming Language :: Python :: 3
Classifier: Programming Language :: Python :: 3.8
Classifier: Programming Language :: Python :: 3.9
Classifier: Programming Language :: Python :: 3.10
Classifier: Programming Language :: Python :: 3.11
Classifier: Operating System :: OS Independent
Classifier: Topic :: Software Development :: Libraries :: Python Modules
Classifier: Topic :: Security
Requires-Python: >=3.8
License-File: LICENSE
Requires-Dist: Django >=3.2
